CHANGELOG.txt
LICENSE.txt
MANIFEST.in
README.txt
setup.py
my_library/__intit__.py
yayati_calc_test_module.egg-info/PKG-INFO
yayati_calc_test_module.egg-info/SOURCES.txt
yayati_calc_test_module.egg-info/dependency_links.txt
yayati_calc_test_module.egg-info/top_level.txt